authress/VERSION
authress/__init__.py
authress/api_response.py
authress/authress_client.py
authress/exceptions.py
authress/http_client.py
authress/py.typed
authress/rest.py
authress/api/__init__.py
authress/api/access_records_api.py
authress/api/accounts_api.py
authress/api/applications_api.py
authress/api/connections_api.py
authress/api/extensions_api.py
authress/api/groups_api.py
authress/api/invites_api.py
authress/api/resource_permissions_api.py
authress/api/roles_api.py
authress/api/service_clients_api.py
authress/api/tenants_api.py
authress/api/token_verifier.py
authress/api/user_permissions_api.py
authress/api/users_api.py
authress/models/__init__.py
authress/models/access_record.py
authress/models/access_record_account.py
authress/models/access_record_collection.py
authress/models/access_request.py
authress/models/access_request_collection.py
authress/models/access_request_response.py
authress/models/access_template.py
authress/models/account.py
authress/models/account_collection.py
authress/models/account_links.py
authress/models/application_delegation.py
authress/models/authentication_token_configuration.py
authress/models/claim_request.py
authress/models/client.py
authress/models/client_access_key.py
authress/models/client_collection.py
authress/models/client_options.py
authress/models/client_rate_limit.py
authress/models/collection_links.py
authress/models/connection.py
authress/models/connection_collection.py
authress/models/connection_conditions.py
authress/models/connection_data.py
authress/models/connection_default_connection_properties.py
authress/models/connection_linking_configuration.py
authress/models/connection_user_data_configuration.py
authress/models/extension.py
authress/models/extension_application.py
authress/models/extension_client.py
authress/models/extension_collection.py
authress/models/group.py
authress/models/group_collection.py
authress/models/identity.py
authress/models/identity_collection.py
authress/models/identity_request.py
authress-3.1.120.dist-info/licenses/LICENSE
authress-3.1.120.dist-info/METADATA
authress-3.1.120.dist-info/WHEEL
authress-3.1.120.dist-info/top_level.txt
authress-3.1.120.dist-info/RECORD
