Metadata-Version: 2.4
Name: authress
Version: 3.1.120
Summary: Authress SDK for authorization as a service and interact with the Authress API.
Home-page: https://github.com/Authress/authress-sdk.py.git
Author: Authress Developers
Author-email: developers@authress.io
License: Apache-2.0
Keywords: Authorization as a service,Security,authorization,authorization as a service,authentication,user authentication,Authress,Authress client,access management,access management as a service,user security,oso,polar,open source policy engine,embedded authorization,batteries included authorization,verified,verified access,verified permissions
License-File: LICENSE
Requires-Dist: urllib3<3,>=1.25.3
Requires-Dist: python-dateutil
Requires-Dist: pydantic<3,>=1.10.5
Requires-Dist: PyJWT>=2.4.0
Requires-Dist: cryptography>=2.9.2
Requires-Dist: aenum
Requires-Dist: certifi>=14.05.14
Requires-Dist: python_dateutil>=2.5.3
Dynamic: author
Dynamic: author-email
Dynamic: description
Dynamic: description-content-type
Dynamic: home-page
Dynamic: keywords
Dynamic: license
Dynamic: license-file
Dynamic: requires-dist
Dynamic: summary
